lazycloud/__init__.py
lazycloud/__main__.py
lazycloud/__version__.py
lazycloud/cli.py
lazycloud/py.typed
lazycloud/aws/__init__.py
lazycloud/aws/tag_manager.py
lazycloud-0.1.0.dist-info/METADATA
lazycloud-0.1.0.dist-info/WHEEL
lazycloud-0.1.0.dist-info/entry_points.txt
lazycloud-0.1.0.dist-info/licenses/LICENSE
lazycloud-0.1.0.dist-info/RECORD
