Metadata-Version: 2.4
Name: lazycloud
Version: 0.1.0
Summary: Cloud operations helper with easy terminal interface
Project-URL: Documentation, https://github.com/makukha/lazycloud#readme
Project-URL: Homepage, https://github.com/makukha/lazycloud
Project-URL: Repository, https://github.com/makukha/lazycloud
Project-URL: Issues, https://github.com/makukha/lazycloud/issues
Project-URL: Changelog, https://github.com/makukha/lazycloud/blob/main/CHANGELOG.md
Author-email: Michael Makukha <m.makukha@gmail.com>
License: MIT
License-File: LICENSE
Keywords: aws,cli,cloud,tui
Classifier: Development Status :: 4 - Beta
Classifier: Environment :: Console
Classifier: Intended Audience :: System Administrators
Classifier: License :: OSI Approved :: MIT License
Classifier: Operating System :: OS Independent
Classifier: Programming Language :: Python
Classifier: Programming Language :: Python :: 3
Classifier: Programming Language :: Python :: 3.11
Classifier: Programming Language :: Python :: 3.12
Classifier: Programming Language :: Python :: 3.13
Classifier: Programming Language :: Python :: Implementation :: CPython
Classifier: Topic :: System :: Distributed Computing
Classifier: Topic :: System :: Systems Administration
Classifier: Topic :: Utilities
Classifier: Typing :: Typed
Requires-Python: >=3.11
Requires-Dist: caseutil>=0.7.2
Requires-Dist: questionary>=2.1.0
Requires-Dist: rich-click>=1.8.9
Requires-Dist: rich>=14.1.0
Provides-Extra: all
Requires-Dist: aiobotocore>=2; extra == 'all'
Requires-Dist: types-aiobotocore[iam,resourcegroupstaggingapi]>=2; extra == 'all'
Provides-Extra: aws
Requires-Dist: aiobotocore>=2; extra == 'aws'
Requires-Dist: types-aiobotocore[iam,resourcegroupstaggingapi]>=2; extra == 'aws'
